ggmpc/__init__.py
ggmpc/__main__.py
ggmpc/curves.py
ggmpc/ecdsa.py
ggmpc/eddsa.py
ggmpc/rand.py
ggmpc/shamir.py
ggmpc/serialization/__init__.py
ggmpc/serialization/ecdsa.py
ggmpc/serialization/eddsa.py
ggmpc/serialization/serialization.py
ggmpc-0.3.0.dist-info/LICENSE
ggmpc-0.3.0.dist-info/METADATA
ggmpc-0.3.0.dist-info/WHEEL
ggmpc-0.3.0.dist-info/entry_points.txt
ggmpc-0.3.0.dist-info/top_level.txt
ggmpc-0.3.0.dist-info/RECORD
