Metadata-Version: 2.1
Name: ggmpc
Version: 0.3.0
Summary: An implementation of MPC threshold signatures
Home-page: https://github.com/johnoliverdriscoll/py-ggmpc
Author: John Driscoll
Author-email: johnoliverdriscoll@gmail.com
License: GPL-3.0-orlater
Project-URL: Bug Tracker, https://github.com/johnoliverdriscoll/py-ggmpc/issues
Requires-Python: >=3.8
License-File: LICENSE
